persistql/__init__.py
persistql-0.0.1.dist-info/METADATA
persistql-0.0.1.dist-info/WHEEL
persistql-0.0.1.dist-info/top_level.txt
persistql-0.0.1.dist-info/RECORD
