Metadata-Version: 2.1
Name: persistql
Version: 0.0.1
Summary: persistql package lock
